pyubee/__init__.py
pyubee/__main__.py
pyubee-0.11.dist-info/LICENSE
pyubee-0.11.dist-info/METADATA
pyubee-0.11.dist-info/WHEEL
pyubee-0.11.dist-info/entry_points.txt
pyubee-0.11.dist-info/top_level.txt
pyubee-0.11.dist-info/RECORD
