Metadata-Version: 2.1
Name: pyubee
Version: 0.11
Summary: Simple library for getting stats from Ubee routers.
Home-page: http://github.com/mzdrale/pyubee
Author: Miroslav Zdrale
Author-email: mzdrale@gmail.com
License: UNKNOWN
Platform: UNKNOWN
Classifier: Programming Language :: Python :: 3
Classifier: License :: OSI Approved :: GNU General Public License v3 or later (GPLv3+)
Classifier: Operating System :: OS Independent
